repeatradar/__init__.py
repeatradar/cohort_generator.py
repeatradar/visualization_generator.py
repeatradar-1.0.0.dist-info/METADATA
repeatradar-1.0.0.dist-info/WHEEL
repeatradar-1.0.0.dist-info/RECORD
