Metadata-Version: 2.3
Name: repeatradar
Version: 1.0.0
Summary: A Python package for analyzing cohort retention and generating insightful visualizations.
License: MIT
Keywords: cohort,retention,calculation,visualization
Author: Kristof Menyhert
Author-email: menyhert.kristof@gmail.com
Requires-Python: >=3.10
Classifier: License :: OSI Approved :: MIT License
Classifier: Programming Language :: Python :: 3
Classifier: Programming Language :: Python :: 3.10
Classifier: Programming Language :: Python :: 3.11
Classifier: Programming Language :: Python :: 3.12
Classifier: Programming Language :: Python :: 3.13
Requires-Dist: datetime (>=5.5,<6.0)
Requires-Dist: numpy (>=2.2.6,<3.0.0)
Requires-Dist: pandas (>=2.2.3,<3.0.0)
Requires-Dist: plotly (>=6.1.2,<7.0.0)
